mintotp.py
mintotp-0.3.0.dist-info/LICENSE.md
mintotp-0.3.0.dist-info/METADATA
mintotp-0.3.0.dist-info/WHEEL
mintotp-0.3.0.dist-info/entry_points.txt
mintotp-0.3.0.dist-info/top_level.txt
mintotp-0.3.0.dist-info/RECORD
