Metadata-Version: 2.1
Name: mintotp
Version: 0.3.0
Summary: MinTOTP - Minimal TOTP Generator
Home-page: https://github.com/susam/mintotp
Author: Susam Pal
Author-email: susam@susam.in
License: MIT
Keywords: totp hotp otp hmac cryptography 2fa authenticator
Platform: UNKNOWN
Classifier: Development Status :: 5 - Production/Stable
Classifier: Environment :: Console
Classifier: Intended Audience :: Developers
Classifier: Intended Audience :: End Users/Desktop
Classifier: License :: OSI Approved :: MIT License
Classifier: Operating System :: OS Independent
Classifier: Programming Language :: Python :: 3
Classifier: Topic :: Security
Classifier: Topic :: Security :: Cryptography
Classifier: Topic :: Software Development
Classifier: Topic :: Software Development :: Libraries
Classifier: Topic :: Utilities
